simple_up_counter/up_counter_4bit.v
module up_counter_4bit (input clk,  
      input reset,  
      output reg [3:0]count);  
always @(posedge clk or posedge reset)   
  begin    
 if(reset)      
 count <= 4'b0000;    
 else   
           count <= count + 1;  
  end  
endmodule

simple_up_counter/up_counter_4bit_tb.v
module up_counter_4bit_tb;  
  reg clk;   reg reset;  
  wire [3:0] count;  
  
up_counter_4bit uut (  
  .clk(clk),  
  .reset(reset),  
  .count(count)  
  );  
  
// clock generation  
always #5 clk <= ~clk; // 10 time unit clock period 
initial        
 begin  
 $monitor("Time=%t|Reset=%b |count=%b",$time,reset,count);   
 reset = 1; #10;    
 reset = 0; #200;  
  $finish;  
end  
initial begin  
  $dumpfile ("up_counter_4bit.vcd");  
  $dumpvars();  
  end  
endmodule

simple_up_counter/obj_dir/up_counter_4bit.vcd
$version Generated by VerilatedVcd $end
$timescale 1ps $end

 $scope module TOP $end
  $scope module up_counter_4bit_tb $end
   $var wire  1 # clk $end
   $var wire  4 % count [3:0] $end
   $var wire  1 $ reset $end
   $scope module uut $end
    $var wire  1 # clk $end
    $var wire  4 % count [3:0] $end
    $var wire  1 $ reset $end
   $upscope $end
  $upscope $end
 $upscope $end
$enddefinitions $end


#0
0#
1$
b0000 %
#5
1#
#10
0#
0$
#15
1#
b0001 %
#20
0#
#25
1#
b0010 %
#30
0#
#35
1#
b0011 %
#40
0#
#45
1#
b0100 %
#50
0#
#55
1#
b0101 %
#60
0#
#65
1#
b0110 %
#70
0#
#75
1#
b0111 %
#80
0#
#85
1#
b1000 %
#90
0#
#95
1#
b1001 %
#100
0#
#105
1#
b1010 %
#110
0#
#115
1#
b1011 %
#120
0#
#125
1#
b1100 %
#130
0#
#135
1#
b1101 %
#140
0#
#145
1#
b1110 %
#150
0#
#155
1#
b1111 %
#160
0#
#165
1#
b0000 %
#170
0#
#175
1#
b0001 %
#180
0#
#185
1#
b0010 %
#190
0#
#195
1#
b0011 %
#200
0#
#205
1#
b0100 %
