apb_uart_interface/uart.v
module uart ( 
input  wire       clk, 
input  wire       rst_n, 
input  wire [7:0] tx_data, 
input  wire       tx_write, 
output reg  [7:0] rx_data, 
output reg        rx_ready, 
output reg        tx_busy 
); 
reg [7:0] tx_reg; 
always @(posedge clk or negedge rst_n) begin 
if (!rst_n) begin 
tx_reg   <= 8'h00; 
rx_data  <= 8'h00; 
rx_ready <= 1'b0; 
tx_busy  <= 1'b0; 
end else begin 
rx_ready <= 1'b0; 
if (tx_write) begin 
tx_reg   <= tx_data; 
tx_busy  <= 1'b1; 
rx_data  <= tx_data; 
rx_ready <= 1'b1; 
tx_busy  <= 1'b0; 
end 
end 
end 
endmodule

apb_uart_interface/apb_uart_bridge.v
module apb_uart_bridge ( 
input  wire        clk, 
input  wire        rst_n, 
input  wire [31:0] PADDR, 
input  wire [31:0] PWDATA, 
input  wire        PWRITE, 
input  wire        PSEL, 
input  wire        PENABLE, 
output reg  [31:0] PRDATA, 
output reg         PREADY 
); 
reg  [7:0] tx_data; 
reg        tx_write; 
wire [7:0] rx_data; 
wire       rx_ready; 
wire       tx_busy; 
uart uart_inst ( 
.clk(clk), 
.rst_n(rst_n), 
.tx_data(tx_data), 
.tx_write(tx_write), 
.rx_data(rx_data), 
.rx_ready(rx_ready), 
.tx_busy(tx_busy) 
); 
always @(posedge clk or negedge rst_n) begin 
if (!rst_n) begin 
PREADY   <= 1'b0; 
PRDATA   <= 32'h0; 
tx_data  <= 8'h00; 
tx_write <= 1'b0; 
end else begin 
PREADY   <= 1'b0; 
tx_write <= 1'b0; 
if (PSEL && PENABLE) begin 
PREADY <= 1'b1; 
if (PWRITE) begin 
case (PADDR[7:0]) 
8'h00: begin 
tx_data  <= PWDATA[7:0]; 
tx_write <= 1'b1; 
end 
endcase 
end else begin 
case (PADDR[7:0]) 
8'h04: PRDATA <= {24'h0, rx_data};// RX data 
8'h08: PRDATA <= {30'h0, tx_busy, rx_ready};       
default: PRDATA <= 32'h0; 
endcase 
end 
end 
end 
end 
endmodule

apb_uart_interface/apb_uart_top.v
module apb_uart_top ( 
input  wire        clk, 
input  wire        rst_n, 
input  wire [31:0] PADDR, 
input  wire [31:0] PWDATA, 
input  wire        PWRITE, 
input  wire        PSEL, 
input  wire        PENABLE, 
output wire [31:0] PRDATA, 
output wire        PREADY 
); 

apb_uart_bridge dut (
.clk(clk),
.rst_n(rst_n),
.PADDR(PADDR),
.PWDATA(PWDATA),
.PWRITE(PWRITE),
.PSEL(PSEL),
.PENABLE(PENABLE),
.PRDATA(PRDATA),
.PREADY(PREADY)
);
endmodule

apb_uart_interface/apb_uart_tb.v
`timescale 1ns/1ps 
module apb_uart_tb; 
reg clk = 0; 
reg rst_n; 
reg [31:0] PADDR; 
reg [31:0] PWDATA; 
reg        PWRITE; 
reg        PSEL; 
reg        PENABLE; 
wire [31:0] PRDATA; 
wire        PREADY; 
apb_uart_top dut ( 
.clk(clk), 
.rst_n(rst_n), 
.PADDR(PADDR), 
.PWDATA(PWDATA), 
.PWRITE(PWRITE), 
.PSEL(PSEL), 
.PENABLE(PENABLE), 
.PRDATA(PRDATA), 
.PREADY(PREADY) 
); 
always #10 clk = ~clk; 
initial begin 
rst_n   = 0; 
PADDR   = 0; 
PWDATA  = 0; 
PWRITE  = 0; 
PSEL    = 0; 
PENABLE = 0; 
#100; 
rst_n = 1; 
// Write TX register 
apb_write(32'h00, 32'hA5); 
// Read RX register 
apb_read(32'h04); 
// Read STATUS register 
apb_read(32'h08); 
// Second transfer 
apb_write(32'h00, 32'h3C); 
apb_read(32'h04); 
apb_read(32'h08); 
#100; 
$finish; 
end 
task apb_write(input [31:0] addr, input [31:0] data); 
begin 
@(posedge clk); 
PADDR   = addr; 
PWDATA  = data; 
PWRITE  = 1; 
PSEL    = 1; 
PENABLE = 0; 
@(posedge clk); 
PENABLE = 1; 
@(posedge clk); 
PSEL    = 0; 
 PENABLE = 0; 
    $display("APB WRITE : ADDR=%h DATA=%h", addr, data); 
end 
endtask 
 
task apb_read(input [31:0] addr); 
begin 
    @(posedge clk); 
    PADDR   = addr; 
    PWRITE  = 0; 
    PSEL    = 1; 
    PENABLE = 0; 
 
    @(posedge clk); 
    PENABLE = 1; 
 
    @(posedge clk);    
    @(posedge clk);  
 
    $display("APB READ  : ADDR=%h DATA=%h", addr, PRDATA); 
 
    PSEL    = 0; 
    PENABLE = 0; 
end 
endtask 
 
initial begin 
    $dumpfile("apb_uart_dump.vcd"); 
    $dumpvars(); 
end 
 
endmodule

apb_uart_interface/obj_dir/apb_uart_dump.vcd
$version Generated by VerilatedVcd $end
$timescale 1ps $end

 $scope module TOP $end
  $scope module apb_uart_tb $end
   $var wire 32 $ PADDR [31:0] $end
   $var wire  1 ( PENABLE $end
   $var wire 32 ) PRDATA [31:0] $end
   $var wire  1 * PREADY $end
   $var wire  1 ' PSEL $end
   $var wire 32 % PWDATA [31:0] $end
   $var wire  1 & PWRITE $end
   $var wire  1 1 clk $end
   $var wire  1 # rst_n $end
   $scope module dut $end
    $var wire 32 $ PADDR [31:0] $end
    $var wire  1 ( PENABLE $end
    $var wire 32 ) PRDATA [31:0] $end
    $var wire  1 * PREADY $end
    $var wire  1 ' PSEL $end
    $var wire 32 % PWDATA [31:0] $end
    $var wire  1 & PWRITE $end
    $var wire  1 1 clk $end
    $var wire  1 # rst_n $end
    $scope module dut $end
     $var wire 32 $ PADDR [31:0] $end
     $var wire  1 ( PENABLE $end
     $var wire 32 ) PRDATA [31:0] $end
     $var wire  1 * PREADY $end
     $var wire  1 ' PSEL $end
     $var wire 32 % PWDATA [31:0] $end
     $var wire  1 & PWRITE $end
     $var wire  1 1 clk $end
     $var wire  1 # rst_n $end
     $var wire  8 - rx_data [7:0] $end
     $var wire  1 . rx_ready $end
     $var wire  1 / tx_busy $end
     $var wire  8 + tx_data [7:0] $end
     $var wire  1 , tx_write $end
     $scope module uart_inst $end
      $var wire  1 1 clk $end
      $var wire  1 # rst_n $end
      $var wire  8 - rx_data [7:0] $end
      $var wire  1 . rx_ready $end
      $var wire  1 / tx_busy $end
      $var wire  8 + tx_data [7:0] $end
      $var wire  8 0 tx_reg [7:0] $end
      $var wire  1 , tx_write $end
     $upscope $end
    $upscope $end
   $upscope $end
  $upscope $end
 $upscope $end
$enddefinitions $end


#0
0#
b00000000000000000000000000000000 $
b00000000000000000000000000000000 %
0&
0'
0(
b00000000000000000000000000000000 )
0*
b00000000 +
0,
b00000000 -
0.
0/
b00000000 0
01
#10000
11
#20000
01
#30000
11
#40000
01
#50000
11
#60000
01
#70000
11
#80000
01
#90000
11
#100000
1#
01
#110000
b00000000000000000000000010100101 %
1&
1'
11
#120000
01
#130000
1(
1*
b10100101 +
1,
11
#140000
01
#150000
0'
0(
0*
0,
b10100101 -
1.
b10100101 0
11
#160000
01
#170000
b00000000000000000000000000000100 $
0&
1'
0.
11
#180000
01
#190000
1(
b00000000000000000000000010100101 )
1*
11
#200000
01
#210000
11
#220000
01
#230000
0'
0(
0*
11
#240000
01
#250000
b00000000000000000000000000001000 $
1'
11
#260000
01
#270000
1(
b00000000000000000000000000000000 )
1*
11
#280000
01
#290000
11
#300000
01
#310000
0'
0(
0*
11
#320000
01
#330000
b00000000000000000000000000000000 $
b00000000000000000000000000111100 %
1&
1'
11
#340000
01
#350000
1(
1*
b00111100 +
1,
11
#360000
01
#370000
0'
0(
0*
0,
b00111100 -
1.
b00111100 0
11
#380000
01
#390000
b00000000000000000000000000000100 $
0&
1'
0.
11
#400000
01
#410000
1(
b00000000000000000000000000111100 )
1*
11
#420000
01
#430000
11
#440000
01
#450000
0'
0(
0*
11
#460000
01
#470000
b00000000000000000000000000001000 $
1'
11
#480000
01
#490000
1(
b00000000000000000000000000000000 )
1*
11
#500000
01
#510000
11
#520000
01
#530000
0'
0(
0*
11
