soc_debug_lab/uart_stub.v
module uart_stub ( 
input clk,               
input rst_n,             
input tx_en,             
input [7:0] tx_data,     
output reg tx_done    
);  
always @(posedge clk or negedge rst_n) begin 
	if (!rst_n) 
tx_done <= 0; 
else if (tx_en) 
tx_done <= 1; 
else 
tx_done <= 0; 
end 
endmodule

soc_debug_lab/alu.v
module alu ( 
input  [3:0] a,      
input  [3:0] b,      
input  sel,         
output reg [3:0] y   
); 
	always @(*) begin 
		case (sel) 
			1'b0: y = a & b;         
			1'b1: y = a + b;
			default: y = 4'b0000; 
		endcase 
	end 
endmodule

soc_debug_lab/soc_top.v
module soc_top (
    input clk,
    input rst_n,
    input [3:0] in1,
    input [3:0] in2,
    input sel,
    input tx_en,
    output tx_done,
    output [3:0] alu_out
);

wire [3:0] alu_result;

// ALU instance for arithmetic/logic operation
alu alu_dut (
    .a(in1),
    .b(in2),
    .sel(sel),
    .y(alu_result)
);

// UART stub instance
uart_stub uart_dut (
    .clk(clk),
    .rst_n(rst_n),
    .tx_en(tx_en),
    .tx_data(alu_result),    // ← Mistake: should be {4'b0000, alu_result}
    .tx_done(tx_done)
);

assign alu_out = alu_result;

endmodule

soc_debug_lab/soc_tb.v
module soc_tb;
    reg clk = 0;
    reg rst_n = 0;
    reg [3:0] in1, in2;
    reg sel;
    reg tx_en;
    wire tx_done;
    wire [3:0] alu_out;

    // Generate clock
    always #5 clk = ~clk;

    // Instantiate the DUT (SoC with Bug)
    soc_top uut (
        .clk(clk),
        .rst_n(rst_n),
        .in1(in1),
        .in2(in2),
        .sel(sel),
        .tx_en(tx_en),
        .tx_done(tx_done),
        .alu_out(alu_out)
    );

    initial begin
        $dumpfile("soc_debug.vcd");
        $dumpvars();

        // Apply reset
        #10 rst_n = 1;

        // Test 1: ADD 4 + 3 = 7, expect UART to transmit 8'b00000111
        in1 = 4; in2 = 3; sel = 1; tx_en = 1;
        #10 tx_en = 0;

        // Test 2: AND 6 & 5 = 4, expect UART to transmit 8'b00000100
        #20 in1 = 6; in2 = 5; sel = 0; tx_en = 1;
        #10 tx_en = 0;

        #40 $finish;
    end
endmodule

soc_debug_lab/obj_dir/soc_debug.vcd
$version Generated by VerilatedVcd $end
$timescale 1ps $end

 $scope module TOP $end
  $scope module soc_tb $end
   $var wire  4 ( alu_out [3:0] $end
   $var wire  1 * clk $end
   $var wire  4 $ in1 [3:0] $end
   $var wire  4 % in2 [3:0] $end
   $var wire  1 # rst_n $end
   $var wire  1 & sel $end
   $var wire  1 + tx_done $end
   $var wire  1 ' tx_en $end
   $scope module uut $end
    $var wire  4 ( alu_out [3:0] $end
    $var wire  4 ( alu_result [3:0] $end
    $var wire  1 * clk $end
    $var wire  4 $ in1 [3:0] $end
    $var wire  4 % in2 [3:0] $end
    $var wire  1 # rst_n $end
    $var wire  1 & sel $end
    $var wire  1 + tx_done $end
    $var wire  1 ' tx_en $end
    $scope module alu_dut $end
     $var wire  4 $ a [3:0] $end
     $var wire  4 % b [3:0] $end
     $var wire  1 & sel $end
     $var wire  4 ( y [3:0] $end
    $upscope $end
    $scope module uart_dut $end
     $var wire  1 * clk $end
     $var wire  1 # rst_n $end
     $var wire  8 ) tx_data [7:0] $end
     $var wire  1 + tx_done $end
     $var wire  1 ' tx_en $end
    $upscope $end
   $upscope $end
  $upscope $end
 $upscope $end
$enddefinitions $end


#0
0#
b0000 $
b0000 %
0&
0'
b0000 (
b00000000 )
0*
0+
#5
1*
#10
1#
b0100 $
b0011 %
1&
1'
b0111 (
b00000111 )
0*
#15
1*
1+
#20
0'
0*
#25
1*
0+
#30
0*
#35
1*
#40
b0110 $
b0101 %
0&
1'
b0100 (
b00000100 )
0*
#45
1*
1+
#50
0'
0*
#55
1*
0+
