cdc_synchronizer/cdc_sync.v
module cdc_synchronizer ( 
input clk,              // Clock input 
input async_in,         // Asynchronous input signal 
output reg synced       // Synchronized output signal 
); 
reg stage1;             // First-stage flip-flop 
// Two-stage flip-flop chain for synchronization 
always @(posedge clk) begin 
stage1 <= async_in; 
synced <= stage1; 
end 
endmodule

cdc_synchronizer/cdc_sync_tb.v
module cdc_sync_tb; 
reg clk = 0;           
reg async_in = 0;      
wire synced; 
always #5 clk = ~clk;
cdc_synchronizer uut ( 
.clk(clk), 
.async_in(async_in), 
.synced(synced) 
); 
// Apply transitions not aligned to clk 
initial begin 
$dumpfile("dump.vcd"); 
$dumpvars(0, cdc_sync_tb); 
#12 async_in = 1; 
#7  async_in = 0; 
#6  async_in = 1; 
#9  async_in = 0; 
#50 $finish; 
end 
endmodule

cdc_synchronizer/obj_dir/dump.vcd
$version Generated by VerilatedVcd $end
$timescale 1ps $end

 $scope module TOP $end
  $scope module cdc_sync_tb $end
   $var wire  1 $ async_in $end
   $var wire  1 # clk $end
   $var wire  1 % synced $end
   $scope module uut $end
    $var wire  1 $ async_in $end
    $var wire  1 # clk $end
    $var wire  1 & stage1 $end
    $var wire  1 % synced $end
   $upscope $end
  $upscope $end
 $upscope $end
$enddefinitions $end


#0
0#
0$
0%
0&
#5
1#
#10
0#
#12
1$
#15
1#
1&
#19
0$
#20
0#
#25
1#
1$
1%
#30
0#
#34
0$
#35
1#
0&
#40
0#
#45
1#
0%
