Down_counter/down_counter_4bit.v
module down_counter_4bit( 
    input clk, 
    input reset, 
    output reg [3:0] count 
); 
always @(posedge clk or posedge reset) begin 
    if(reset) 
        count <= 4'b1111; 
    else 
        count <= count - 1; 
end 
endmodule

Down_counter/down_counter_tb.v
module down_counter_tb; 
reg clk; 
reg reset; 
wire [3:0] count; 
down_counter_4bit uut ( 
.clk(clk), 
.reset(reset), 
.count(count) 
); 
always #5 clk <= ~clk; 
initial begin 
clk = 0;   
$monitor("Time=%t|Reset=%b|count=%b",$time,reset,count); 
reset = 1; #10; 
reset = 0; #200; 
$finish; 
end 
initial begin 
$dumpfile("down_counter_4bit.vcd"); 
$dumpvars(); 
end 
endmodule

Down_counter/obj_dir/down_counter_4bit.vcd
$version Generated by VerilatedVcd $end
$timescale 1ps $end

 $scope module TOP $end
  $scope module down_counter_tb $end
   $var wire  1 # clk $end
   $var wire  4 % count [3:0] $end
   $var wire  1 $ reset $end
   $scope module uut $end
    $var wire  1 # clk $end
    $var wire  4 % count [3:0] $end
    $var wire  1 $ reset $end
   $upscope $end
  $upscope $end
 $upscope $end
$enddefinitions $end


#0
0#
1$
b0000 %
#5
1#
b1111 %
#10
0#
0$
#15
1#
b1110 %
#20
0#
#25
1#
b1101 %
#30
0#
#35
1#
b1100 %
#40
0#
#45
1#
b1011 %
#50
0#
#55
1#
b1010 %
#60
0#
#65
1#
b1001 %
#70
0#
#75
1#
b1000 %
#80
0#
#85
1#
b0111 %
#90
0#
#95
1#
b0110 %
#100
0#
#105
1#
b0101 %
#110
0#
#115
1#
b0100 %
#120
0#
#125
1#
b0011 %
#130
0#
#135
1#
b0010 %
#140
0#
#145
1#
b0001 %
#150
0#
#155
1#
b0000 %
#160
0#
#165
1#
b1111 %
#170
0#
#175
1#
b1110 %
#180
0#
#185
1#
b1101 %
#190
0#
#195
1#
b1100 %
#200
0#
#205
1#
b1011 %
