apb_timer/apb_timer.v
 
`timescale 1ns/1ps 
 
module apb_timer #( 
    parameter WIDTH = 8   // Counter width 
)(
// APB interface 
input  wire        PCLK,      // APB clock 
input  wire        PRESETn,   // Active-low reset 
input  wire        PSEL,      // Peripheral select 
input  wire        PENABLE,   // Access phase indicator 
input  wire        PWRITE,    // 1 = write, 0 = read 
input  wire [7:0]  PADDR,     // Register address 
input  wire [31:0] PWDATA,    // Write data 
output reg  [31:0] PRDATA,    // Read data 
// Timer status output 
output reg         timer_done 
); 
// Internal timer registers 
reg [WIDTH-1:0] load_val;     // Programmed timer value 
reg [WIDTH-1:0] count;        // Active counter 
reg             running;      // Timer enable 
// APB write path 
// Valid write: PSEL=1, PENABLE=1, PWRITE=1 
always @(posedge PCLK or negedge PRESETn) begin 
if (!PRESETn) begin 
load_val <= 0; 
running  <= 0; 
end 
else if (PSEL && PENABLE && PWRITE) begin 
case (PADDR) 
8'h00: load_val <= PWDATA[WIDTH-1:0]; 
8'h04: running  <= PWDATA[0]; 
endcase 
end 
end 
// APB read path 
// Valid read: PSEL=1, PWRITE=0 
always @(*) begin 
PRDATA = 32'h0; 
if (PSEL && !PWRITE) begin 
case (PADDR) 
8'h00: PRDATA = {{(32-WIDTH){1'b0}}, load_val}; 
8'h04: PRDATA = {31'b0, running}; 
 8'h08: PRDATA = {31'b0, timer_done}; 
                default: PRDATA = 32'h0; 
            endcase 
        end 
    end 
 
    // Timer logic 
    // Counter decrements while running 
    // On reaching zero, timer_done is asserted 
    always @(posedge PCLK or negedge PRESETn) begin 
        if (!PRESETn) begin 
            count      <= 0; 
            timer_done <= 0; 
        end 
        else if (running) begin 
            if (count == 0) begin 
                count      <= load_val; 
                timer_done <= 1; 
                running    <= 0; 
            end 
            else begin 
                count      <= count - 1; 
                timer_done <= 0; 
            end 
        end 
    end 
 
endmodule

apb_timer/apb_timer_tb.v
`timescale 1ns/1ps 
module apb_timer_tb; 
 
    // APB interface signals 
    reg         PCLK; 
    reg         PRESETn = 0; 
    reg         PSEL    = 0; 
    reg         PENABLE = 0; 
    reg         PWRITE  = 0; 
  reg  [7:0]  PADDR   = 0; 
    reg  [31:0] PWDATA  = 0; 
    wire [31:0] PRDATA; 
    wire        timer_done; 
 
    // DUT instance 
    apb_timer uut ( 
        .PCLK(PCLK), 
        .PRESETn(PRESETn), 
        .PSEL(PSEL), 
        .PENABLE(PENABLE), 
        .PWRITE(PWRITE), 
        .PADDR(PADDR), 
        .PWDATA(PWDATA), 
        .PRDATA(PRDATA), 
        .timer_done(timer_done) 
    ); 
 
    // Clock generation 
    initial PCLK = 0; 
    always #5 PCLK = ~PCLK; 
 
    // Monitor timer completion 
    always @(posedge timer_done) 
        $display("Time=%0t : TIMER DONE", $time); 
 
    // APB write task 
    task apb_write(input [7:0] addr, input [31:0] data); 
    begin 
     @(posedge PCLK); 
        PSEL = 1; PWRITE = 1; PENABLE = 0; PADDR = addr; 
PWDATA = data; 
        @(posedge PCLK); 
        PENABLE = 1; 
        @(posedge PCLK); 
        PSEL = 0; PENABLE = 0; PWRITE = 0; 
    end 
    endtask 
 
    // APB read task 
    task apb_read(input [7:0] addr); 
    begin 
        @(posedge PCLK);
PSEL = 1; PWRITE = 0; PENABLE = 0; PADDR = addr; 
@(posedge PCLK); 
PENABLE = 1; 
@(posedge PCLK); 
$display("Read [0x%0h] = %0d", addr, PRDATA); 
PSEL = 0; PENABLE = 0; 
end 
endtask 
// Test sequence 
initial begin 
$dumpfile("apb_timer.vcd"); 
$dumpvars(0, apb_timer_tb); 
// Apply reset 
#10 PRESETn = 1; 
// Program load value = 5 
apb_write(8'h00, 5); 
// Start timer 
apb_write(8'h04, 1); 
// Wait and read status 
#80 apb_read(8'h08); 
// Program load value = 3 
apb_write(8'h00, 3); 
// Start timer again 
apb_write(8'h04, 1); 
// Read status delay 
#50 apb_read(8'h08); 
#50 $finish; 
end 
endmodule

apb_timer/obj_dir/apb_timer.vcd
$version Generated by VerilatedVcd $end
$timescale 1ps $end

 $scope module TOP $end
  $scope module apb_timer_tb $end
   $var wire  8 ' PADDR [7:0] $end
   $var wire  1 - PCLK $end
   $var wire  1 % PENABLE $end
   $var wire 32 . PRDATA [31:0] $end
   $var wire  1 # PRESETn $end
   $var wire  1 $ PSEL $end
   $var wire 32 ( PWDATA [31:0] $end
   $var wire  1 & PWRITE $end
   $var wire  1 ) timer_done $end
   $scope module uut $end
    $var wire  8 ' PADDR [7:0] $end
    $var wire  1 - PCLK $end
    $var wire  1 % PENABLE $end
    $var wire 32 . PRDATA [31:0] $end
    $var wire  1 # PRESETn $end
    $var wire  1 $ PSEL $end
    $var wire 32 ( PWDATA [31:0] $end
    $var wire  1 & PWRITE $end
    $var wire 32 / WIDTH [31:0] $end
    $var wire  8 + count [7:0] $end
    $var wire  8 * load_val [7:0] $end
    $var wire  1 , running $end
    $var wire  1 ) timer_done $end
   $upscope $end
  $upscope $end
 $upscope $end
$enddefinitions $end


#0
0#
0$
0%
0&
b00000000 '
b00000000000000000000000000000000 (
0)
b00000000 *
b00000000 +
0,
0-
b00000000000000000000000000000000 .
b00000000000000000000000000001000 /
#5000
1-
#10000
1#
0-
#15000
1$
1&
b00000000000000000000000000000101 (
1-
#20000
0-
#25000
1%
b00000101 *
1-
#30000
0-
#35000
0$
0%
0&
1-
#40000
0-
#45000
1$
1&
b00000100 '
b00000000000000000000000000000001 (
1-
#50000
0-
#55000
1%
1,
1-
#60000
0-
#65000
0$
0%
0&
1)
b00000101 +
0,
1-
#70000
0-
#75000
1-
#80000
0-
#85000
1-
#90000
0-
#95000
1-
#100000
0-
#105000
1-
#110000
0-
#115000
1-
#120000
0-
#125000
1-
#130000
0-
#135000
1-
#140000
0-
#145000
1-
#150000
0-
#155000
1$
b00001000 '
1-
b00000000000000000000000000000001 .
#160000
0-
#165000
1%
1-
#170000
0-
#175000
0$
0%
1-
b00000000000000000000000000000000 .
#180000
0-
#185000
1$
1&
b00000000 '
b00000000000000000000000000000011 (
1-
#190000
0-
#195000
1%
b00000011 *
1-
#200000
0-
#205000
0$
0%
0&
1-
#210000
0-
#215000
1$
1&
b00000100 '
b00000000000000000000000000000001 (
1-
#220000
0-
#225000
1%
1,
1-
#230000
0-
#235000
0$
0%
0&
0)
b00000100 +
1-
#240000
0-
#245000
b00000011 +
1-
#250000
0-
#255000
b00000010 +
1-
#260000
0-
#265000
b00000001 +
1-
#270000
0-
#275000
b00000000 +
1-
#280000
0-
#285000
1)
b00000011 +
0,
1-
#290000
0-
#295000
1$
b00001000 '
1-
b00000000000000000000000000000001 .
#300000
0-
#305000
1%
1-
#310000
0-
#315000
0$
0%
1-
b00000000000000000000000000000000 .
