sync_logic_demo/cdc_sync.v
module cdc_sync ( 
input clk,             
input async_in,        
output reg sync_out    
); 
reg stage1;
always @(posedge clk) begin 
stage1   <= async_in;     
sync_out <= stage1;       
end 
endmodule

sync_logic_demo/reset_sync.v
module reset_sync ( 
input clk,              
input async_reset,     
output reg sync_reset );
reg sync_ff1;          
always @(posedge clk or posedge async_reset) begin 
if (async_reset) begin 
sync_ff1     <= 1'b1; 
sync_reset   <= 1'b1; 
end else begin 
sync_ff1     <= 1'b0; 
sync_reset   <= sync_ff1; 
end 
end 
endmodule

sync_logic_demo/top_with_sync.v
module top_with_sync (
    input clk,              // Main clock input
    input async_reset,      // Global asynchronous reset
    input async_signal,     // CDC input from another domain
    output synced_reset,    // Cleaned reset
    output synced_signal    // Cleaned signal
);

// Instantiate the reset synchronizer
reset_sync u_reset_sync (
    .clk(clk),
    .async_reset(async_reset),
    .sync_reset(synced_reset)
);

// Instantiate the 2-stage CDC synchronizer
cdc_sync u_cdc_sync (
    .clk(clk),
    .async_in(async_signal),
    .sync_out(synced_signal)
);

endmodule

sync_logic_demo/sync_tb.v
module sync_tb;

reg clk = 0;
reg async_reset = 1;
reg async_signal = 0;
wire synced_reset;
wire synced_signal;

// Generate clock
always #5 clk = ~clk;

// Instantiate DUT
top_with_sync dut (
    .clk(clk),
    .async_reset(async_reset),
    .async_signal(async_signal),
    .synced_reset(synced_reset),
    .synced_signal(synced_signal)
);

initial begin
    $dumpfile("dump.vcd");
    $dumpvars(0, sync_tb);

    // Deassert reset after some time
    #12 async_reset = 0;

    // Inject asynchronous signal pulses
    #15 async_signal = 1;
    #3  async_signal = 0;

    #20 async_signal = 1;
    #2  async_signal = 0;

    #40 $finish;
end

endmodule

sync_logic_demo/obj_dir/dump.vcd
$version Generated by VerilatedVcd $end
$timescale 1ps $end

 $scope module TOP $end
  $scope module sync_tb $end
   $var wire  1 $ async_reset $end
   $var wire  1 % async_signal $end
   $var wire  1 # clk $end
   $var wire  1 & synced_reset $end
   $var wire  1 ' synced_signal $end
   $scope module dut $end
    $var wire  1 $ async_reset $end
    $var wire  1 % async_signal $end
    $var wire  1 # clk $end
    $var wire  1 & synced_reset $end
    $var wire  1 ' synced_signal $end
    $scope module u_cdc_sync $end
     $var wire  1 % async_in $end
     $var wire  1 # clk $end
     $var wire  1 ( stage1 $end
     $var wire  1 ' sync_out $end
    $upscope $end
    $scope module u_reset_sync $end
     $var wire  1 $ async_reset $end
     $var wire  1 # clk $end
     $var wire  1 ) sync_ff1 $end
     $var wire  1 & sync_reset $end
    $upscope $end
   $upscope $end
  $upscope $end
 $upscope $end
$enddefinitions $end


#0
0#
1$
0%
0&
0'
0(
0)
#5
1#
1&
1)
#10
0#
#12
0$
#15
1#
0)
#20
0#
#25
1#
0&
#27
1%
#30
0#
0%
#35
1#
#40
0#
#45
1#
#50
0#
1%
#52
0%
