ripple_up_counter/tff.v
module tff ( 
    input clk, 
    input reset, 
    output reg q 
); 
    always @(posedge clk or posedge reset) begin 
        if (reset) 
            q <= 1'b0;  
        else 
            q <= ~q; 
    end 
endmodule

ripple_up_counter/ripple_up_counter_4bit.v
module ripple_up_counter_4bit ( 
    input clk, 
    input reset, 
    output [3:0] q 
 
); 
    wire q_out0, q_out1, q_out2, q_out3; 
    assign q = {q_out3, q_out2, q_out1, q_out0}; 
    // TFF instantiation 
    tff tff0 (.clk(clk),       .reset(reset), .q(q_out0)); 
    tff tff1 (.clk(~q_out0),   .reset(reset), .q(q_out1)); 
    tff tff2 (.clk(~q_out1),   .reset(reset), .q(q_out2)); 
    tff tff3 (.clk(~q_out2),   .reset(reset), .q(q_out3)); 
endmodule

ripple_up_counter/ripple_up_counter_4bit_tb.v
module ripple_up_counter_4bit_tb; 
reg clk; 
reg reset; 
wire [3:0] q; 
// 4-bit ripple up counter instantiation 
ripple_up_counter_4bit uut ( 
.clk(clk), 
.reset(reset), 
.q(q) 
); 
// Clock generation 
always #5 clk <= ~clk; 
initial begin 
clk = 0; 
reset = 1; 
// Display signals 
$display("Time\treset\tq"); 
$monitor("%0dns\t%b\t%b", $time, reset, q); 
// Apply reset 
#10; 
reset = 0; 
#200; 
$finish; 
end 
// Waveform dump 
initial begin 
$dumpfile("up_counter_dump.vcd"); 
$dumpvars(); 
end 
endmodule

ripple_up_counter/obj_dir/up_counter_dump.vcd
$version Generated by VerilatedVcd $end
$timescale 1ps $end

 $scope module TOP $end
  $scope module ripple_up_counter_4bit_tb $end
   $var wire  1 # clk $end
   $var wire  4 % q [3:0] $end
   $var wire  1 $ reset $end
   $scope module uut $end
    $var wire  1 # clk $end
    $var wire  4 % q [3:0] $end
    $var wire  1 & q_out0 $end
    $var wire  1 ' q_out1 $end
    $var wire  1 ( q_out2 $end
    $var wire  1 ) q_out3 $end
    $var wire  1 $ reset $end
    $scope module tff0 $end
     $var wire  1 # clk $end
     $var wire  1 & q $end
     $var wire  1 $ reset $end
    $upscope $end
    $scope module tff1 $end
     $var wire  1 * clk $end
     $var wire  1 ' q $end
     $var wire  1 $ reset $end
    $upscope $end
    $scope module tff2 $end
     $var wire  1 + clk $end
     $var wire  1 ( q $end
     $var wire  1 $ reset $end
    $upscope $end
    $scope module tff3 $end
     $var wire  1 , clk $end
     $var wire  1 ) q $end
     $var wire  1 $ reset $end
    $upscope $end
   $upscope $end
  $upscope $end
 $upscope $end
$enddefinitions $end


#0
0#
1$
b0000 %
0&
0'
0(
0)
1*
1+
1,
#5
1#
#10
0#
0$
#15
1#
b0001 %
1&
0*
#20
0#
#25
1#
b0010 %
0&
1'
1*
0+
#30
0#
#35
1#
b0011 %
1&
0*
#40
0#
#45
1#
b0100 %
0&
0'
1(
1*
1+
0,
#50
0#
#55
1#
b0101 %
1&
0*
#60
0#
#65
1#
b0110 %
0&
1'
1*
0+
#70
0#
#75
1#
b0111 %
1&
0*
#80
0#
#85
1#
b1000 %
0&
0'
0(
1)
1*
1+
1,
#90
0#
#95
1#
b1001 %
1&
0*
#100
0#
#105
1#
b1010 %
0&
1'
1*
0+
#110
0#
#115
1#
b1011 %
1&
0*
#120
0#
#125
1#
b1100 %
0&
0'
1(
1*
1+
0,
#130
0#
#135
1#
b1101 %
1&
0*
#140
0#
#145
1#
b1110 %
0&
1'
1*
0+
#150
0#
#155
1#
b1111 %
1&
0*
#160
0#
#165
1#
b0000 %
0&
0'
0(
0)
1*
1+
1,
#170
0#
#175
1#
b0001 %
1&
0*
#180
0#
#185
1#
b0010 %
0&
1'
1*
0+
#190
0#
#195
1#
b0011 %
1&
0*
#200
0#
#205
1#
b0100 %
0&
0'
1(
1*
1+
0,
