timer_ip_lab/simple_timer.v
`timescale 1ns/1ps 
module simple_timer #( 
parameter WIDTH = 8   // Width of timer counter 
)( 
input  wire              clk,       // System clock 
input  wire              rst,       // Synchronous reset 
input  wire              start,     // Start the timer 
input  wire [WIDTH-1:0]  load_val,  // Initial countdown   
output reg               done       // High when timer 
); 
reg [WIDTH-1:0] count;   // Timer counter register 
reg             running; // Indicates timer is active 
always @(posedge clk or posedge rst) begin 
if (rst) begin 
count   <= 0; 
running <= 0; 
done    <= 0; 
end else begin 
if (start) begin 
// Load the preset value and start counting 
count   <= load_val; 
running <= 1; 
done    <= 0; 
end else if (running) begin 
if (count > 0) begin 
count <= count - 1;   // Decrement counter 
end else begin 
running <= 0;         // Stop timer 
done    <= 1;         // Raise done signal 
end 
end 
end 
end 
endmodule

timer_ip_lab/simple_timer_tb.v
`timescale 1ns/1ps 
module simple_timer_tb; 
reg clk = 0; 
reg rst = 1; 
reg start = 0; 
reg [7:0] load_val = 0; 
wire done; 
// Instantiate Timer DUT 
simple_timer #(.WIDTH(8)) uut ( 
.clk(clk), 
.rst(rst), 
.start(start), 
.load_val(load_val), 
.done(done) 
);
// Clock generation 
always #5 clk = ~clk; 
initial begin 
$dumpfile("simple_timer.vcd"); 
$dumpvars(0, simple_timer_tb); 
// Reset 
#10 rst = 0; 
// Start timer with value 5 
#5  load_val = 8'd5; start = 1; 
#10 start = 0; 
// Wait for timer to finish 
#100; 
// Start timer again with value 3 
#5  load_val = 8'd3; start = 1; 
#10 start = 0; 
#50 $finish; 
end 
endmodule

timer_ip_lab/obj_dir/simple_timer.vcd
$version Generated by VerilatedVcd $end
$timescale 1ps $end

 $scope module TOP $end
  $scope module simple_timer_tb $end
   $var wire  1 & clk $end
   $var wire  1 # done $end
   $var wire  8 ) load_val [7:0] $end
   $var wire  1 ' rst $end
   $var wire  1 ( start $end
   $scope module uut $end
    $var wire 32 * WIDTH [31:0] $end
    $var wire  1 & clk $end
    $var wire  8 $ count [7:0] $end
    $var wire  1 # done $end
    $var wire  8 ) load_val [7:0] $end
    $var wire  1 ' rst $end
    $var wire  1 % running $end
    $var wire  1 ( start $end
   $upscope $end
  $upscope $end
 $upscope $end
$enddefinitions $end


#0
0#
b00000000 $
0%
0&
1'
0(
b00000000 )
b00000000000000000000000000001000 *
#5000
1&
#10000
0&
0'
#15000
b00000101 $
1%
1&
1(
b00000101 )
#20000
0&
#25000
b00000100 $
1&
0(
#30000
0&
#35000
b00000011 $
1&
#40000
0&
#45000
b00000010 $
1&
#50000
0&
#55000
b00000001 $
1&
#60000
0&
#65000
b00000000 $
1&
#70000
0&
#75000
1#
0%
1&
#80000
0&
#85000
1&
#90000
0&
#95000
1&
#100000
0&
#105000
1&
#110000
0&
#115000
1&
#120000
0&
#125000
1&
#130000
0&
1(
b00000011 )
#135000
0#
b00000011 $
1%
1&
#140000
0&
0(
#145000
b00000010 $
1&
#150000
0&
#155000
b00000001 $
1&
#160000
0&
#165000
b00000000 $
1&
#170000
0&
#175000
1#
0%
1&
